README.md
setup.py
ekfrcnn/__init__.py
ekfrcnn/functions.py
ekfrcnn.kfrcnn.egg-info/PKG-INFO
ekfrcnn.kfrcnn.egg-info/SOURCES.txt
ekfrcnn.kfrcnn.egg-info/dependency_links.txt
ekfrcnn.kfrcnn.egg-info/top_level.txt
ekfrcnn/kfrcnn/FixedBatchNormalization.py
ekfrcnn/kfrcnn/RoiPoolingConv.py
ekfrcnn/kfrcnn/__init__.py
ekfrcnn/kfrcnn/config.py
ekfrcnn/kfrcnn/data_augment.py
ekfrcnn/kfrcnn/data_generators.py
ekfrcnn/kfrcnn/losses.py
ekfrcnn/kfrcnn/pascal_voc_parser.py
ekfrcnn/kfrcnn/resnet.py
ekfrcnn/kfrcnn/roi_helpers.py
ekfrcnn/kfrcnn/simple_parser.py
ekfrcnn/kfrcnn/vgg.py