Metadata-Version: 1.0
Name: ekfrcnn.kfrcnn
Version: 0.0.2
Summary: This package provide a simple interface to use the Faster RCNN architecture
Home-page: UNKNOWN
Author: Italo José G. de Oliveira
Author-email: italo.i@live.com
License: MIT license
Platform: UNKNOWN
